LICENSE
MANIFEST.in
NOTICE
README.md
requirements.txt
setup.py
Punisher.egg-info/PKG-INFO
Punisher.egg-info/SOURCES.txt
Punisher.egg-info/dependency_links.txt
Punisher.egg-info/not-zip-safe
Punisher.egg-info/top_level.txt
punisher/__init__.py
punisher/_constants.py